Workbook

Sheet 日本预估利润表
A1: 日本头程预估贡献利润表 · 一张表只计算一票货
A2: 蓝色 A–I 列为输入，绿色 J–V 列为公式。删除示例行输入值后填真实数据；每行数据须完整，否则显示 #N/A。
A3: 这是离线计算器，不是网站上传模板。网站上传请下载「头程利润预估」CSV 模板；英国、德国规则尚未提供。
A4: 产品名称 | B4: MSKU | C4: 数量 | D4: 总CBM | E4: 箱数 | F4: 出厂价RMB/件 | G4: 申报售价JPY/件 | H4: 销售价JPY/件 | I4: 平台佣金及尾程JPY/件 | J4: 海运RMB | K4: 国内RMB | L4: 税金JPY | M4: 税金RMB | N4: 贴标RMB | O4: 固定费分摊RMB | P4: 头程总RMB | Q4: 单件头程RMB | R4: 采购总RMB | S4: 销售额RMB | T4: 平台总RMB | U4: 贡献利润RMB | V4: 贡献利润率
A5: 示例产品1 | B5: EXAMPLE-1 | C5: 100 | D5: 1 | E5: 10 | F5: 20 | G5: 2000 | H5: 3000 | I5: 800 | J5: =IF(COUNTA(A5:I5)=0,"",IF(OR(COUNT(C5:I5)<>7,C5<=0,D5<=0,E5<=0),NA(),D5*'参数与逻辑'!$B$2)) | K5: =IF(J5="","",D5*'参数与逻辑'!$B$3) | L5: =IF(J5="","",G5*C5*'参数与逻辑'!$B$4*'参数与逻辑'!$B$5) | M5: =IF(J5="","",L5*'参数与逻辑'!$B$9) | N5: =IF(J5="","",E5*'参数与逻辑'!$B$6) | O5: =IF(J5="","",('参数与逻辑'!$B$7+'参数与逻辑'!$B$8)*D5/SUM($D$5:$D$24)) | P5: =IF(J5="","",J5+K5+M5+N5+O5) | Q5: =IF(J5="","",P5/C5) | R5: =IF(J5="","",F5*C5) | S5: =IF(J5="","",H5*C5*'参数与逻辑'!$B$9) | T5: =IF(J5="","",I5*C5*'参数与逻辑'!$B$9) | U5: =IF(J5="","",S5-R5-P5-T5) | V5: =IF(J5="","",IF(S5=0,"",U5/S5))
A6: 示例产品2 | B6: EXAMPLE-2 | C6: 100 | D6: 3 | E6: 10 | F6: 20 | G6: 2000 | H6: 3000 | I6: 800 | J6: =IF(COUNTA(A6:I6)=0,"",IF(OR(COUNT(C6:I6)<>7,C6<=0,D6<=0,E6<=0),NA(),D6*'参数与逻辑'!$B$2)) | K6: =IF(J6="","",D6*'参数与逻辑'!$B$3) | L6: =IF(J6="","",G6*C6*'参数与逻辑'!$B$4*'参数与逻辑'!$B$5) | M6: =IF(J6="","",L6*'参数与逻辑'!$B$9) | N6: =IF(J6="","",E6*'参数与逻辑'!$B$6) | O6: =IF(J6="","",('参数与逻辑'!$B$7+'参数与逻辑'!$B$8)*D6/SUM($D$5:$D$24)) | P6: =IF(J6="","",J6+K6+M6+N6+O6) | Q6: =IF(J6="","",P6/C6) | R6: =IF(J6="","",F6*C6) | S6: =IF(J6="","",H6*C6*'参数与逻辑'!$B$9) | T6: =IF(J6="","",I6*C6*'参数与逻辑'!$B$9) | U6: =IF(J6="","",S6-R6-P6-T6) | V6: =IF(J6="","",IF(S6=0,"",U6/S6))
J7: =IF(COUNTA(A7:I7)=0,"",IF(OR(COUNT(C7:I7)<>7,C7<=0,D7<=0,E7<=0),NA(),D7*'参数与逻辑'!$B$2)) | K7: =IF(J7="","",D7*'参数与逻辑'!$B$3) | L7: =IF(J7="","",G7*C7*'参数与逻辑'!$B$4*'参数与逻辑'!$B$5) | M7: =IF(J7="","",L7*'参数与逻辑'!$B$9) | N7: =IF(J7="","",E7*'参数与逻辑'!$B$6) | O7: =IF(J7="","",('参数与逻辑'!$B$7+'参数与逻辑'!$B$8)*D7/SUM($D$5:$D$24)) | P7: =IF(J7="","",J7+K7+M7+N7+O7) | Q7: =IF(J7="","",P7/C7) | R7: =IF(J7="","",F7*C7) | S7: =IF(J7="","",H7*C7*'参数与逻辑'!$B$9) | T7: =IF(J7="","",I7*C7*'参数与逻辑'!$B$9) | U7: =IF(J7="","",S7-R7-P7-T7) | V7: =IF(J7="","",IF(S7=0,"",U7/S7))
J8: =IF(COUNTA(A8:I8)=0,"",IF(OR(COUNT(C8:I8)<>7,C8<=0,D8<=0,E8<=0),NA(),D8*'参数与逻辑'!$B$2)) | K8: =IF(J8="","",D8*'参数与逻辑'!$B$3) | L8: =IF(J8="","",G8*C8*'参数与逻辑'!$B$4*'参数与逻辑'!$B$5) | M8: =IF(J8="","",L8*'参数与逻辑'!$B$9) | N8: =IF(J8="","",E8*'参数与逻辑'!$B$6) | O8: =IF(J8="","",('参数与逻辑'!$B$7+'参数与逻辑'!$B$8)*D8/SUM($D$5:$D$24)) | P8: =IF(J8="","",J8+K8+M8+N8+O8) | Q8: =IF(J8="","",P8/C8) | R8: =IF(J8="","",F8*C8) | S8: =IF(J8="","",H8*C8*'参数与逻辑'!$B$9) | T8: =IF(J8="","",I8*C8*'参数与逻辑'!$B$9) | U8: =IF(J8="","",S8-R8-P8-T8) | V8: =IF(J8="","",IF(S8=0,"",U8/S8))
J9: =IF(COUNTA(A9:I9)=0,"",IF(OR(COUNT(C9:I9)<>7,C9<=0,D9<=0,E9<=0),NA(),D9*'参数与逻辑'!$B$2)) | K9: =IF(J9="","",D9*'参数与逻辑'!$B$3) | L9: =IF(J9="","",G9*C9*'参数与逻辑'!$B$4*'参数与逻辑'!$B$5) | M9: =IF(J9="","",L9*'参数与逻辑'!$B$9) | N9: =IF(J9="","",E9*'参数与逻辑'!$B$6) | O9: =IF(J9="","",('参数与逻辑'!$B$7+'参数与逻辑'!$B$8)*D9/SUM($D$5:$D$24)) | P9: =IF(J9="","",J9+K9+M9+N9+O9) | Q9: =IF(J9="","",P9/C9) | R9: =IF(J9="","",F9*C9) | S9: =IF(J9="","",H9*C9*'参数与逻辑'!$B$9) | T9: =IF(J9="","",I9*C9*'参数与逻辑'!$B$9) | U9: =IF(J9="","",S9-R9-P9-T9) | V9: =IF(J9="","",IF(S9=0,"",U9/S9))
J10: =IF(COUNTA(A10:I10)=0,"",IF(OR(COUNT(C10:I10)<>7,C10<=0,D10<=0,E10<=0),NA(),D10*'参数与逻辑'!$B$2)) | K10: =IF(J10="","",D10*'参数与逻辑'!$B$3) | L10: =IF(J10="","",G10*C10*'参数与逻辑'!$B$4*'参数与逻辑'!$B$5) | M10: =IF(J10="","",L10*'参数与逻辑'!$B$9) | N10: =IF(J10="","",E10*'参数与逻辑'!$B$6) | O10: =IF(J10="","",('参数与逻辑'!$B$7+'参数与逻辑'!$B$8)*D10/SUM($D$5:$D$24)) | P10: =IF(J10="","",J10+K10+M10+N10+O10) | Q10: =IF(J10="","",P10/C10) | R10: =IF(J10="","",F10*C10) | S10: =IF(J10="","",H10*C10*'参数与逻辑'!$B$9) | T10: =IF(J10="","",I10*C10*'参数与逻辑'!$B$9) | U10: =IF(J10="","",S10-R10-P10-T10) | V10: =IF(J10="","",IF(S10=0,"",U10/S10))
J11: =IF(COUNTA(A11:I11)=0,"",IF(OR(COUNT(C11:I11)<>7,C11<=0,D11<=0,E11<=0),NA(),D11*'参数与逻辑'!$B$2)) | K11: =IF(J11="","",D11*'参数与逻辑'!$B$3) | L11: =IF(J11="","",G11*C11*'参数与逻辑'!$B$4*'参数与逻辑'!$B$5) | M11: =IF(J11="","",L11*'参数与逻辑'!$B$9) | N11: =IF(J11="","",E11*'参数与逻辑'!$B$6) | O11: =IF(J11="","",('参数与逻辑'!$B$7+'参数与逻辑'!$B$8)*D11/SUM($D$5:$D$24)) | P11: =IF(J11="","",J11+K11+M11+N11+O11) | Q11: =IF(J11="","",P11/C11) | R11: =IF(J11="","",F11*C11) | S11: =IF(J11="","",H11*C11*'参数与逻辑'!$B$9) | T11: =IF(J11="","",I11*C11*'参数与逻辑'!$B$9) | U11: =IF(J11="","",S11-R11-P11-T11) | V11: =IF(J11="","",IF(S11=0,"",U11/S11))
J12: =IF(COUNTA(A12:I12)=0,"",IF(OR(COUNT(C12:I12)<>7,C12<=0,D12<=0,E12<=0),NA(),D12*'参数与逻辑'!$B$2)) | K12: =IF(J12="","",D12*'参数与逻辑'!$B$3) | L12: =IF(J12="","",G12*C12*'参数与逻辑'!$B$4*'参数与逻辑'!$B$5) | M12: =IF(J12="","",L12*'参数与逻辑'!$B$9) | N12: =IF(J12="","",E12*'参数与逻辑'!$B$6) | O12: =IF(J12="","",('参数与逻辑'!$B$7+'参数与逻辑'!$B$8)*D12/SUM($D$5:$D$24)) | P12: =IF(J12="","",J12+K12+M12+N12+O12) | Q12: =IF(J12="","",P12/C12) | R12: =IF(J12="","",F12*C12) | S12: =IF(J12="","",H12*C12*'参数与逻辑'!$B$9) | T12: =IF(J12="","",I12*C12*'参数与逻辑'!$B$9) | U12: =IF(J12="","",S12-R12-P12-T12) | V12: =IF(J12="","",IF(S12=0,"",U12/S12))
J13: =IF(COUNTA(A13:I13)=0,"",IF(OR(COUNT(C13:I13)<>7,C13<=0,D13<=0,E13<=0),NA(),D13*'参数与逻辑'!$B$2)) | K13: =IF(J13="","",D13*'参数与逻辑'!$B$3) | L13: =IF(J13="","",G13*C13*'参数与逻辑'!$B$4*'参数与逻辑'!$B$5) | M13: =IF(J13="","",L13*'参数与逻辑'!$B$9) | N13: =IF(J13="","",E13*'参数与逻辑'!$B$6) | O13: =IF(J13="","",('参数与逻辑'!$B$7+'参数与逻辑'!$B$8)*D13/SUM($D$5:$D$24)) | P13: =IF(J13="","",J13+K13+M13+N13+O13) | Q13: =IF(J13="","",P13/C13) | R13: =IF(J13="","",F13*C13) | S13: =IF(J13="","",H13*C13*'参数与逻辑'!$B$9) | T13: =IF(J13="","",I13*C13*'参数与逻辑'!$B$9) | U13: =IF(J13="","",S13-R13-P13-T13) | V13: =IF(J13="","",IF(S13=0,"",U13/S13))
J14: =IF(COUNTA(A14:I14)=0,"",IF(OR(COUNT(C14:I14)<>7,C14<=0,D14<=0,E14<=0),NA(),D14*'参数与逻辑'!$B$2)) | K14: =IF(J14="","",D14*'参数与逻辑'!$B$3) | L14: =IF(J14="","",G14*C14*'参数与逻辑'!$B$4*'参数与逻辑'!$B$5) | M14: =IF(J14="","",L14*'参数与逻辑'!$B$9) | N14: =IF(J14="","",E14*'参数与逻辑'!$B$6) | O14: =IF(J14="","",('参数与逻辑'!$B$7+'参数与逻辑'!$B$8)*D14/SUM($D$5:$D$24)) | P14: =IF(J14="","",J14+K14+M14+N14+O14) | Q14: =IF(J14="","",P14/C14) | R14: =IF(J14="","",F14*C14) | S14: =IF(J14="","",H14*C14*'参数与逻辑'!$B$9) | T14: =IF(J14="","",I14*C14*'参数与逻辑'!$B$9) | U14: =IF(J14="","",S14-R14-P14-T14) | V14: =IF(J14="","",IF(S14=0,"",U14/S14))
J15: =IF(COUNTA(A15:I15)=0,"",IF(OR(COUNT(C15:I15)<>7,C15<=0,D15<=0,E15<=0),NA(),D15*'参数与逻辑'!$B$2)) | K15: =IF(J15="","",D15*'参数与逻辑'!$B$3) | L15: =IF(J15="","",G15*C15*'参数与逻辑'!$B$4*'参数与逻辑'!$B$5) | M15: =IF(J15="","",L15*'参数与逻辑'!$B$9) | N15: =IF(J15="","",E15*'参数与逻辑'!$B$6) | O15: =IF(J15="","",('参数与逻辑'!$B$7+'参数与逻辑'!$B$8)*D15/SUM($D$5:$D$24)) | P15: =IF(J15="","",J15+K15+M15+N15+O15) | Q15: =IF(J15="","",P15/C15) | R15: =IF(J15="","",F15*C15) | S15: =IF(J15="","",H15*C15*'参数与逻辑'!$B$9) | T15: =IF(J15="","",I15*C15*'参数与逻辑'!$B$9) | U15: =IF(J15="","",S15-R15-P15-T15) | V15: =IF(J15="","",IF(S15=0,"",U15/S15))
J16: =IF(COUNTA(A16:I16)=0,"",IF(OR(COUNT(C16:I16)<>7,C16<=0,D16<=0,E16<=0),NA(),D16*'参数与逻辑'!$B$2)) | K16: =IF(J16="","",D16*'参数与逻辑'!$B$3) | L16: =IF(J16="","",G16*C16*'参数与逻辑'!$B$4*'参数与逻辑'!$B$5) | M16: =IF(J16="","",L16*'参数与逻辑'!$B$9) | N16: =IF(J16="","",E16*'参数与逻辑'!$B$6) | O16: =IF(J16="","",('参数与逻辑'!$B$7+'参数与逻辑'!$B$8)*D16/SUM($D$5:$D$24)) | P16: =IF(J16="","",J16+K16+M16+N16+O16) | Q16: =IF(J16="","",P16/C16) | R16: =IF(J16="","",F16*C16) | S16: =IF(J16="","",H16*C16*'参数与逻辑'!$B$9) | T16: =IF(J16="","",I16*C16*'参数与逻辑'!$B$9) | U16: =IF(J16="","",S16-R16-P16-T16) | V16: =IF(J16="","",IF(S16=0,"",U16/S16))
J17: =IF(COUNTA(A17:I17)=0,"",IF(OR(COUNT(C17:I17)<>7,C17<=0,D17<=0,E17<=0),NA(),D17*'参数与逻辑'!$B$2)) | K17: =IF(J17="","",D17*'参数与逻辑'!$B$3) | L17: =IF(J17="","",G17*C17*'参数与逻辑'!$B$4*'参数与逻辑'!$B$5) | M17: =IF(J17="","",L17*'参数与逻辑'!$B$9) | N17: =IF(J17="","",E17*'参数与逻辑'!$B$6) | O17: =IF(J17="","",('参数与逻辑'!$B$7+'参数与逻辑'!$B$8)*D17/SUM($D$5:$D$24)) | P17: =IF(J17="","",J17+K17+M17+N17+O17) | Q17: =IF(J17="","",P17/C17) | R17: =IF(J17="","",F17*C17) | S17: =IF(J17="","",H17*C17*'参数与逻辑'!$B$9) | T17: =IF(J17="","",I17*C17*'参数与逻辑'!$B$9) | U17: =IF(J17="","",S17-R17-P17-T17) | V17: =IF(J17="","",IF(S17=0,"",U17/S17))
J18: =IF(COUNTA(A18:I18)=0,"",IF(OR(COUNT(C18:I18)<>7,C18<=0,D18<=0,E18<=0),NA(),D18*'参数与逻辑'!$B$2)) | K18: =IF(J18="","",D18*'参数与逻辑'!$B$3) | L18: =IF(J18="","",G18*C18*'参数与逻辑'!$B$4*'参数与逻辑'!$B$5) | M18: =IF(J18="","",L18*'参数与逻辑'!$B$9) | N18: =IF(J18="","",E18*'参数与逻辑'!$B$6) | O18: =IF(J18="","",('参数与逻辑'!$B$7+'参数与逻辑'!$B$8)*D18/SUM($D$5:$D$24)) | P18: =IF(J18="","",J18+K18+M18+N18+O18) | Q18: =IF(J18="","",P18/C18) | R18: =IF(J18="","",F18*C18) | S18: =IF(J18="","",H18*C18*'参数与逻辑'!$B$9) | T18: =IF(J18="","",I18*C18*'参数与逻辑'!$B$9) | U18: =IF(J18="","",S18-R18-P18-T18) | V18: =IF(J18="","",IF(S18=0,"",U18/S18))
... J24: =IF(COUNTA(A24:I24)=0,"",IF(OR(COUNT(C24:I24)<>7,C24<=0,D24<=0,E24<=0),NA(),D24*'参数与逻辑'!$B$2)) | K24: =IF(J24="","",D24*'参数与逻辑'!$B$3) | L24: =IF(J24="","",G24*C24*'参数与逻辑'!$B$4*'参数与逻辑'!$B$5) | M24: =IF(J24="","",L24*'参数与逻辑'!$B$9) | N24: =IF(J24="","",E24*'参数与逻辑'!$B$6) | O24: =IF(J24="","",('参数与逻辑'!$B$7+'参数与逻辑'!$B$8)*D24/SUM($D$5:$D$24)) | P24: =IF(J24="","",J24+K24+M24+N24+O24) | Q24: =IF(J24="","",P24/C24) | R24: =IF(J24="","",F24*C24) | S24: =IF(J24="","",H24*C24*'参数与逻辑'!$B$9) | T24: =IF(J24="","",I24*C24*'参数与逻辑'!$B$9) | U24: =IF(J24="","",S24-R24-P24-T24) | V24: =IF(J24="","",IF(S24=0,"",U24/S24))
A26: 整票合计（人民币，税金 L 列为日元） | C26: =SUM(C5:C24) | D26: =SUM(D5:D24) | E26: =SUM(E5:E24) | J26: =SUM(J5:J24) | K26: =SUM(K5:K24) | L26: =SUM(L5:L24) | M26: =SUM(M5:M24) | N26: =SUM(N5:N24) | O26: =SUM(O5:O24) | P26: =SUM(P5:P24) | R26: =SUM(R5:R24) | S26: =SUM(S5:S24) | T26: =SUM(T5:T24) | U26: =SUM(U5:U24) | V26: =IF(S26=0,"",U26/S26)

Sheet 参数与逻辑
A1: 参数 | B1: 暂定值（可调整）
A2: 海运人民币/CBM | B2: 800
A3: 国内人民币/CBM | B3: 200
A4: 税基系数 | B4: 0.29
A5: 税率 | B5: 0.13
A6: 贴标人民币/箱 | B6: 4
A7: 清关人民币/整票 | B7: 1500
A8: 报关人民币/整票 | B8: 350
A9: 日元兑人民币 | B9: 0.047
A10: 固定费分摊 | B10: (清关+报关) × 单款CBM / 整票CBM，仅计一次
A11: 税金人民币 | B11: 申报售价JPY × 数量 × 税基系数 × 税率 × 汇率
A12: 贡献利润 | B12: 销售额人民币 − 采购成本 − 头程 − 平台佣金及尾程

Sheet 使用说明
A1: 使用说明
A2: 每张表对应一票货，可填 20 款产品。不要将多票费用放入同表。
A3: 价格币种：出厂价人民币，申报售价/销售价/平台单件费日元；汇率人民币/日元。
A4: 固定清关 1500 + 报关 350 为整票人民币费用，按 CBM 占比分摊。
A5: 删除两条示例行 A–I 的输入值后再填真实记录；不要删除公式列。
A6: 贡献利润不含广告、仓储、退款等未录入费用，不是最终净利润。
A7: 预估参数暂定，不是实际账单。实际加权成本使用网站「实际头程账单」功能。
A8: 历史加权公式：(历史基数数量×历史单价 + 新批次实际总额) ÷ 总数量。
A9: 历史基数截至日期后才计入新实际账单，避免重复成本。
A10: 不支持英国、德国：需要用户提供指定技能正文后实现。
A11: Excel 打开时自动重新计算公式；本文件不会读取或同步网站库存。
